timingstack/__init__.py
timingstack/reporting.py
timingstack/timingstack.py
timingstack-0.1.5.dist-info/METADATA
timingstack-0.1.5.dist-info/WHEEL
timingstack-0.1.5.dist-info/RECORD
