Metadata-Version: 2.4
Name: timingstack
Version: 0.1.5
Summary: A powerful timing and performance measurement library for Python applications
Project-URL: Homepage, https://github.com/tintty1/timingstack
Project-URL: Repository, https://github.com/tintty1/timingstack
Project-URL: Documentation, https://github.com/tintty1/timingstack
License: MIT
Keywords: benchmarking,measurement,performance,profiling,timing
Classifier: Intended Audience :: Developers
Classifier: License :: OSI Approved :: MIT License
Classifier: Programming Language :: Python :: 3
Classifier: Programming Language :: Python :: 3.10
Classifier: Programming Language :: Python :: 3.11
Classifier: Programming Language :: Python :: 3.12
Classifier: Topic :: Software Development :: Libraries :: Python Modules
Classifier: Topic :: Software Development :: Testing
Classifier: Topic :: System :: Monitoring
Requires-Python: >=3.10
Provides-Extra: test
Requires-Dist: pytest-asyncio>=0.21.0; extra == 'test'
Requires-Dist: pytest>=7.0.0; extra == 'test'
